csp_adapter_discord/__init__.py
csp_adapter_discord/adapter.py
csp_adapter_discord/adapter_config.py
csp_adapter_discord/example.py
csp_adapter_discord/tests/test_adapter.py
csp_adapter_discord-0.1.2.dist-info/METADATA
csp_adapter_discord-0.1.2.dist-info/WHEEL
csp_adapter_discord-0.1.2.dist-info/licenses/LICENSE
csp_adapter_discord-0.1.2.dist-info/RECORD
