Metadata-Version: 2.4
Name: csp-adapter-discord
Version: 0.1.2
Summary: CSP adapter for Discord
Project-URL: Repository, https://github.com/timkpaine/csp-adapter-discord
Project-URL: Homepage, https://github.com/timkpaine/csp-adapter-discord
Author-email: the csp-adapter-discord authors <t.paine154@gmail.com>
License: Apache-2.0
License-File: LICENSE
Keywords: chat,chatbot,csp,slack,stream-processing
Classifier: Development Status :: 3 - Alpha
Classifier: License :: OSI Approved :: Apache Software License
Classifier: Programming Language :: Python
Classifier: Programming Language :: Python :: 3
Classifier: Programming Language :: Python :: 3.9
Classifier: Programming Language :: Python :: 3.10
Classifier: Programming Language :: Python :: 3.11
Classifier: Programming Language :: Python :: 3.12
Classifier: Programming Language :: Python :: 3.13
Classifier: Programming Language :: Python :: Implementation :: CPython
Classifier: Programming Language :: Python :: Implementation :: PyPy
Requires-Python: >=3.9
Requires-Dist: csp
Requires-Dist: discord-py
Requires-Dist: pydantic>=2
Provides-Extra: develop
Requires-Dist: build; extra == 'develop'
Requires-Dist: bump-my-version; extra == 'develop'
Requires-Dist: check-manifest; extra == 'develop'
Requires-Dist: codespell<2.5,>=2.2.6; extra == 'develop'
Requires-Dist: hatchling; extra == 'develop'
Requires-Dist: mdformat-tables<1.1,>=1; extra == 'develop'
Requires-Dist: mdformat<0.8,>=0.7.17; extra == 'develop'
Requires-Dist: pytest; extra == 'develop'
Requires-Dist: pytest-cov; extra == 'develop'
Requires-Dist: ruff<0.10,>=0.5; extra == 'develop'
Requires-Dist: twine<7,>=5; extra == 'develop'
Requires-Dist: wheel; extra == 'develop'
